{
  "dimension": {
    "space-between": {
      "coupled": {
        "value": "{dimension.space.50}",
        "type": "dimension"
      },
      "repeating-small": {
        "value": "{dimension.space.75}",
        "type": "dimension",
        "comment": "Gap between pills, child elements, etc."
      },
      "repeating-medium": {
        "value": "{dimension.space.100}",
        "type": "dimension",
        "comment": "Gap between cards, etc."
      },
      "related-small": {
        "value": "{dimension.space.100}",
        "type": "dimension"
      },
      "related-medium": {
        "value": "{dimension.space.200}",
        "type": "dimension"
      },
      "separated": {
        "value": "{dimension.space.300}",
        "type": "dimension"
      }
    },
    "space-around": {
      "x-small": {
        "value": "{dimension.space.100}",
        "type": "dimension"
      },
      "small": {
        "value": "{dimension.space.150}",
        "type": "dimension"
      },
      "medium": {
        "value": "{dimension.space.200}",
        "type": "dimension"
      },
      "large": {
        "value": "{dimension.space.250}",
        "type": "dimension"
      }
    },
    "radius": {
      "none": {
        "value": "{dimension.space.0}",
        "type": "dimension"
      },
      "x-small": {
        "value": "{dimension.space.50}",
        "type": "dimension"
      },
      "small": {
        "value": "{dimension.space.100}",
        "type": "dimension"
      },
      "medium": {
        "value": "{dimension.space.200}",
        "type": "dimension"
      },
      "large": {
        "value": "{dimension.space.300}",
        "type": "dimension"
      },
      "x-large": {
        "value": "{dimension.space.400}",
        "type": "dimension"
      }
    }
  }
}